LICENSE
README.md
setup.py
nasr_search/__init__.py
nasr_search/nasr_search.py
nasr_search.egg-info/PKG-INFO
nasr_search.egg-info/SOURCES.txt
nasr_search.egg-info/dependency_links.txt
nasr_search.egg-info/entry_points.txt
nasr_search.egg-info/requires.txt
nasr_search.egg-info/top_level.txt