Metadata-Version: 2.1
Name: nasr-search
Version: 0.2.0
Summary: Search for values in XLSX files.
Author: Eslam
Author-email: eslam.mostafa000@gmail.com
Classifier: Programming Language :: Python :: 3
Classifier: License :: OSI Approved :: MIT License
Classifier: Operating System :: OS Independent
Requires-Python: >=3.6
License-File: LICENSE
